{
 "displayFieldName": "uuid",
 "fieldAliases": {
  "OBJECTID": "OBJECTID",
  "createdate": "createdate",
  "gurasid": "gurasid",
  "principaladdresssiteoid": "principaladdresssiteoid",
  "propertytype": "PropertyType",
  "valnetpropertystatus": "valnetpropertystatus",
  "valnetpropertytype": "valnetpropertytype",
  "dissolveparcelcount": "dissolveparcelcount",
  "valnetlotcount": "valnetlotcount",
  "valnetworkflowid": "valnetworkflowid",
  "propid": "propid",
  "uuid": "uuid",
  "urbanity": "urbanity",
  "superlot": "superlot",
  "housenumber": "housenumber",
  "address": "address",
  "_x_centroid": "_x_centroid",
  "_y_centroid": "_y_centroid",
  "shape_Length": "shape_Length",
  "shape_Area": "shape_Area"
 },
 "geometryType": "esriGeometryPolygon",
 "spatialReference": {
  "wkid": 102100,
  "latestWkid": 3857
 },
 "fields": [
  {
   "name": "OBJECTID",
   "type": "esriFieldTypeOID",
   "alias": "OBJECTID"
  },
  {
   "name": "createdate",
   "type": "esriFieldTypeDate",
   "alias": "createdate",
   "length": 8
  },
  {
   "name": "gurasid",
   "type": "esriFieldTypeInteger",
   "alias": "gurasid"
  },
  {
   "name": "principaladdresssiteoid",
   "type": "esriFieldTypeInteger",
   "alias": "principaladdresssiteoid"
  },
  {
   "name": "propertytype",
   "type": "esriFieldTypeInteger",
   "alias": "PropertyType"
  },
  {
   "name": "valnetpropertystatus",
   "type": "esriFieldTypeInteger",
   "alias": "valnetpropertystatus"
  },
  {
   "name": "valnetpropertytype",
   "type": "esriFieldTypeInteger",
   "alias": "valnetpropertytype"
  },
  {
   "name": "dissolveparcelcount",
   "type": "esriFieldTypeInteger",
   "alias": "dissolveparcelcount"
  },
  {
   "name": "valnetlotcount",
   "type": "esriFieldTypeInteger",
   "alias": "valnetlotcount"
  },
  {
   "name": "valnetworkflowid",
   "type": "esriFieldTypeInteger",
   "alias": "valnetworkflowid"
  },
  {
   "name": "propid",
   "type": "esriFieldTypeInteger",
   "alias": "propid"
  },
  {
   "name": "uuid",
   "type": "esriFieldTypeString",
   "alias": "uuid",
   "length": 50
  },
  {
   "name": "urbanity",
   "type": "esriFieldTypeString",
   "alias": "urbanity",
   "length": 1
  },
  {
   "name": "superlot",
   "type": "esriFieldTypeString",
   "alias": "superlot",
   "length": 1
  },
  {
   "name": "housenumber",
   "type": "esriFieldTypeString",
   "alias": "housenumber",
   "length": 20
  },
  {
   "name": "address",
   "type": "esriFieldTypeString",
   "alias": "address",
   "length": 100
  },
  {
   "name": "_x_centroid",
   "type": "esriFieldTypeDouble",
   "alias": "_x_centroid"
  },
  {
   "name": "_y_centroid",
   "type": "esriFieldTypeDouble",
   "alias": "_y_centroid"
  },
  {
   "name": "shape_Length",
   "type": "esriFieldTypeDouble",
   "alias": "shape_Length"
  },
  {
   "name": "shape_Area",
   "type": "esriFieldTypeDouble",
   "alias": "shape_Area"
  }
 ],
 "features": [
  {
   "attributes": {
    "OBJECTID": 3369090,
    "createdate": 1300536652000,
    "gurasid": 51716618,
    "principaladdresssiteoid": 2187733,
    "propertytype": 1,
    "valnetpropertystatus": 2,
    "valnetpropertytype": 2,
    "dissolveparcelcount": 2,
    "valnetlotcount": 2,
    "valnetworkflowid": null,
    "propid": 1756262,
    "uuid": "6fb1e207-36f7-3abb-a79f-8f3a015d1f35",
    "urbanity": "U",
    "superlot": "N",
    "housenumber": "12",
    "address": "12 WITHERS STREET BEXHILL",
    "_x_centroid": null,
    "_y_centroid": null,
    "shape_Length": 568.08952825198844,
    "shape_Area": 17696.100643590427
   },
   "geometry": {
    "rings": [
     [
      [
       17070463.655249998,
       -3345913.066624999
      ],
      [
       17070453.516000003,
       -3345976.9326249994
      ],
      [
       17070376.402874999,
       -3345962.3822499998
      ],
      [
       17070363.650124997,
       -3345959.9757499993
      ],
      [
       17070333.934749998,
       -3345954.3671250008
      ],
      [
       17070326.964625001,
       -3345953.0511250012
      ],
      [
       17070332.969750002,
       -3345916.7947500013
      ],
      [
       17070337.905249998,
       -3345886.9951249994
      ],
      [
       17070300.090125002,
       -3345880.1570000015
      ],
      [
       17070325.768250003,
       -3345826.4648750015
      ],
      [
       17070395.119874999,
       -3345839.3747499995
      ],
      [
       17070432.498875,
       -3345846.3323750012
      ],
      [
       17070473.050125003,
       -3345853.8817499988
      ],
      [
       17070463.655249998,
       -3345913.066624999
      ]
     ]
    ]
   }
  }
 ]
}