{
 "displayFieldName": "uuid",
 "fieldAliases": {
  "OBJECTID": "OBJECTID",
  "createdate": "createdate",
  "gurasid": "gurasid",
  "principaladdresssiteoid": "principaladdresssiteoid",
  "propertytype": "PropertyType",
  "valnetpropertystatus": "valnetpropertystatus",
  "valnetpropertytype": "valnetpropertytype",
  "dissolveparcelcount": "dissolveparcelcount",
  "valnetlotcount": "valnetlotcount",
  "valnetworkflowid": "valnetworkflowid",
  "propid": "propid",
  "uuid": "uuid",
  "urbanity": "urbanity",
  "superlot": "superlot",
  "housenumber": "housenumber",
  "address": "address",
  "_x_centroid": "_x_centroid",
  "_y_centroid": "_y_centroid",
  "shape_Length": "shape_Length",
  "shape_Area": "shape_Area"
 },
 "geometryType": "esriGeometryPolygon",
 "spatialReference": {
  "wkid": 102100,
  "latestWkid": 3857
 },
 "fields": [
  {
   "name": "OBJECTID",
   "type": "esriFieldTypeOID",
   "alias": "OBJECTID"
  },
  {
   "name": "createdate",
   "type": "esriFieldTypeDate",
   "alias": "createdate",
   "length": 8
  },
  {
   "name": "gurasid",
   "type": "esriFieldTypeInteger",
   "alias": "gurasid"
  },
  {
   "name": "principaladdresssiteoid",
   "type": "esriFieldTypeInteger",
   "alias": "principaladdresssiteoid"
  },
  {
   "name": "propertytype",
   "type": "esriFieldTypeInteger",
   "alias": "PropertyType"
  },
  {
   "name": "valnetpropertystatus",
   "type": "esriFieldTypeInteger",
   "alias": "valnetpropertystatus"
  },
  {
   "name": "valnetpropertytype",
   "type": "esriFieldTypeInteger",
   "alias": "valnetpropertytype"
  },
  {
   "name": "dissolveparcelcount",
   "type": "esriFieldTypeInteger",
   "alias": "dissolveparcelcount"
  },
  {
   "name": "valnetlotcount",
   "type": "esriFieldTypeInteger",
   "alias": "valnetlotcount"
  },
  {
   "name": "valnetworkflowid",
   "type": "esriFieldTypeInteger",
   "alias": "valnetworkflowid"
  },
  {
   "name": "propid",
   "type": "esriFieldTypeInteger",
   "alias": "propid"
  },
  {
   "name": "uuid",
   "type": "esriFieldTypeString",
   "alias": "uuid",
   "length": 50
  },
  {
   "name": "urbanity",
   "type": "esriFieldTypeString",
   "alias": "urbanity",
   "length": 1
  },
  {
   "name": "superlot",
   "type": "esriFieldTypeString",
   "alias": "superlot",
   "length": 1
  },
  {
   "name": "housenumber",
   "type": "esriFieldTypeString",
   "alias": "housenumber",
   "length": 20
  },
  {
   "name": "address",
   "type": "esriFieldTypeString",
   "alias": "address",
   "length": 100
  },
  {
   "name": "_x_centroid",
   "type": "esriFieldTypeDouble",
   "alias": "_x_centroid"
  },
  {
   "name": "_y_centroid",
   "type": "esriFieldTypeDouble",
   "alias": "_y_centroid"
  },
  {
   "name": "shape_Length",
   "type": "esriFieldTypeDouble",
   "alias": "shape_Length"
  },
  {
   "name": "shape_Area",
   "type": "esriFieldTypeDouble",
   "alias": "shape_Area"
  }
 ],
 "features": [
  {
   "attributes": {
    "OBJECTID": 2288932,
    "createdate": 1135036800000,
    "gurasid": 50322755,
    "principaladdresssiteoid": 860800,
    "propertytype": 1,
    "valnetpropertystatus": 2,
    "valnetpropertytype": 2,
    "dissolveparcelcount": 1,
    "valnetlotcount": 1,
    "valnetworkflowid": null,
    "propid": 1331360,
    "uuid": "8580333d-0011-3dbe-8b39-8adf3e66cc3e",
    "urbanity": "U",
    "superlot": "N",
    "housenumber": "130",
    "address": "130 AUBURN ROAD BIRRONG",
    "_x_centroid": null,
    "_y_centroid": null,
    "shape_Length": 727.61019947409284,
    "shape_Area": 29441.161466539037
   },
   "geometry": {
    "rings": [
     [
      [
       16811590.184625,
       -4014839.9895000011
      ],
      [
       16811584.508749999,
       -4014873.4352499992
      ],
      [
       16811345.813375004,
       -4014831.3891250007
      ],
      [
       16811366.16375,
       -4014711.8446249999
      ],
      [
       16811387.921250001,
       -4014715.6001249999
      ],
      [
       16811407.686999999,
       -4014719.0503749996
      ],
      [
       16811427.575374998,
       -4014722.5222500004
      ],
      [
       16811445.944124997,
       -4014725.728374999
      ],
      [
       16811464.004500002,
       -4014728.8803750016
      ],
      [
       16811483.765249997,
       -4014732.3293749988
      ],
      [
       16811501.701875001,
       -4014735.4598749988
      ],
      [
       16811521.684124999,
       -4014738.9473749995
      ],
      [
       16811539.661750004,
       -4014742.0850000009
      ],
      [
       16811557.652249999,
       -4014745.2382499985
      ],
      [
       16811604.866250001,
       -4014753.4814999998
      ],
      [
       16811594.623125002,
       -4014813.8351249993
      ],
      [
       16811590.184625,
       -4014839.9895000011
      ]
     ]
    ]
   }
  }
 ]
}