{
 "displayFieldName": "uuid",
 "fieldAliases": {
  "OBJECTID": "OBJECTID",
  "createdate": "createdate",
  "gurasid": "gurasid",
  "principaladdresssiteoid": "principaladdresssiteoid",
  "propertytype": "PropertyType",
  "valnetpropertystatus": "valnetpropertystatus",
  "valnetpropertytype": "valnetpropertytype",
  "dissolveparcelcount": "dissolveparcelcount",
  "valnetlotcount": "valnetlotcount",
  "valnetworkflowid": "valnetworkflowid",
  "propid": "propid",
  "uuid": "uuid",
  "urbanity": "urbanity",
  "superlot": "superlot",
  "housenumber": "housenumber",
  "address": "address",
  "_x_centroid": "_x_centroid",
  "_y_centroid": "_y_centroid",
  "shape_Length": "shape_Length",
  "shape_Area": "shape_Area"
 },
 "geometryType": "esriGeometryPolygon",
 "spatialReference": {
  "wkid": 102100,
  "latestWkid": 3857
 },
 "fields": [
  {
   "name": "OBJECTID",
   "type": "esriFieldTypeOID",
   "alias": "OBJECTID"
  },
  {
   "name": "createdate",
   "type": "esriFieldTypeDate",
   "alias": "createdate",
   "length": 8
  },
  {
   "name": "gurasid",
   "type": "esriFieldTypeInteger",
   "alias": "gurasid"
  },
  {
   "name": "principaladdresssiteoid",
   "type": "esriFieldTypeInteger",
   "alias": "principaladdresssiteoid"
  },
  {
   "name": "propertytype",
   "type": "esriFieldTypeInteger",
   "alias": "PropertyType"
  },
  {
   "name": "valnetpropertystatus",
   "type": "esriFieldTypeInteger",
   "alias": "valnetpropertystatus"
  },
  {
   "name": "valnetpropertytype",
   "type": "esriFieldTypeInteger",
   "alias": "valnetpropertytype"
  },
  {
   "name": "dissolveparcelcount",
   "type": "esriFieldTypeInteger",
   "alias": "dissolveparcelcount"
  },
  {
   "name": "valnetlotcount",
   "type": "esriFieldTypeInteger",
   "alias": "valnetlotcount"
  },
  {
   "name": "valnetworkflowid",
   "type": "esriFieldTypeInteger",
   "alias": "valnetworkflowid"
  },
  {
   "name": "propid",
   "type": "esriFieldTypeInteger",
   "alias": "propid"
  },
  {
   "name": "uuid",
   "type": "esriFieldTypeString",
   "alias": "uuid",
   "length": 50
  },
  {
   "name": "urbanity",
   "type": "esriFieldTypeString",
   "alias": "urbanity",
   "length": 1
  },
  {
   "name": "superlot",
   "type": "esriFieldTypeString",
   "alias": "superlot",
   "length": 1
  },
  {
   "name": "housenumber",
   "type": "esriFieldTypeString",
   "alias": "housenumber",
   "length": 20
  },
  {
   "name": "address",
   "type": "esriFieldTypeString",
   "alias": "address",
   "length": 100
  },
  {
   "name": "_x_centroid",
   "type": "esriFieldTypeDouble",
   "alias": "_x_centroid"
  },
  {
   "name": "_y_centroid",
   "type": "esriFieldTypeDouble",
   "alias": "_y_centroid"
  },
  {
   "name": "shape_Length",
   "type": "esriFieldTypeDouble",
   "alias": "shape_Length"
  },
  {
   "name": "shape_Area",
   "type": "esriFieldTypeDouble",
   "alias": "shape_Area"
  }
 ],
 "features": [
  {
   "attributes": {
    "OBJECTID": 2780213,
    "createdate": 1330374789000,
    "gurasid": 50960706,
    "principaladdresssiteoid": 2583071,
    "propertytype": 1,
    "valnetpropertystatus": 2,
    "valnetpropertytype": 2,
    "dissolveparcelcount": 1,
    "valnetlotcount": 1,
    "valnetworkflowid": null,
    "propid": 1825413,
    "uuid": "548f2ca1-f296-3104-a8ca-f7e97fb2c9ac",
    "urbanity": "S",
    "superlot": "N",
    "housenumber": "813",
    "address": "813 NUMINBAH ROAD CRYSTAL CREEK",
    "_x_centroid": null,
    "_y_centroid": null,
    "shape_Length": 600.37781778492069,
    "shape_Area": 20108.999636305816
   },
   "geometry": {
    "rings": [
     [
      [
       17068258.442000002,
       -3288330.7391249985
      ],
      [
       17068241.804624997,
       -3288436.1423749998
      ],
      [
       17068039.633000001,
       -3288403.8683749996
      ],
      [
       17068046.034374997,
       -3288340.2873749994
      ],
      [
       17068054.158,
       -3288326.6848750003
      ],
      [
       17068063.738499999,
       -3288316.5177499987
      ],
      [
       17068258.442000002,
       -3288330.7391249985
      ]
     ]
    ]
   }
  }
 ]
}