{
 "displayFieldName": "uuid",
 "fieldAliases": {
  "OBJECTID": "OBJECTID",
  "createdate": "createdate",
  "gurasid": "gurasid",
  "principaladdresssiteoid": "principaladdresssiteoid",
  "propertytype": "PropertyType",
  "valnetpropertystatus": "valnetpropertystatus",
  "valnetpropertytype": "valnetpropertytype",
  "dissolveparcelcount": "dissolveparcelcount",
  "valnetlotcount": "valnetlotcount",
  "valnetworkflowid": "valnetworkflowid",
  "propid": "propid",
  "uuid": "uuid",
  "urbanity": "urbanity",
  "superlot": "superlot",
  "housenumber": "housenumber",
  "address": "address",
  "_x_centroid": "_x_centroid",
  "_y_centroid": "_y_centroid",
  "shape_Length": "shape_Length",
  "shape_Area": "shape_Area"
 },
 "geometryType": "esriGeometryPolygon",
 "spatialReference": {
  "wkid": 102100,
  "latestWkid": 3857
 },
 "fields": [
  {
   "name": "OBJECTID",
   "type": "esriFieldTypeOID",
   "alias": "OBJECTID"
  },
  {
   "name": "createdate",
   "type": "esriFieldTypeDate",
   "alias": "createdate",
   "length": 8
  },
  {
   "name": "gurasid",
   "type": "esriFieldTypeInteger",
   "alias": "gurasid"
  },
  {
   "name": "principaladdresssiteoid",
   "type": "esriFieldTypeInteger",
   "alias": "principaladdresssiteoid"
  },
  {
   "name": "propertytype",
   "type": "esriFieldTypeInteger",
   "alias": "PropertyType"
  },
  {
   "name": "valnetpropertystatus",
   "type": "esriFieldTypeInteger",
   "alias": "valnetpropertystatus"
  },
  {
   "name": "valnetpropertytype",
   "type": "esriFieldTypeInteger",
   "alias": "valnetpropertytype"
  },
  {
   "name": "dissolveparcelcount",
   "type": "esriFieldTypeInteger",
   "alias": "dissolveparcelcount"
  },
  {
   "name": "valnetlotcount",
   "type": "esriFieldTypeInteger",
   "alias": "valnetlotcount"
  },
  {
   "name": "valnetworkflowid",
   "type": "esriFieldTypeInteger",
   "alias": "valnetworkflowid"
  },
  {
   "name": "propid",
   "type": "esriFieldTypeInteger",
   "alias": "propid"
  },
  {
   "name": "uuid",
   "type": "esriFieldTypeString",
   "alias": "uuid",
   "length": 50
  },
  {
   "name": "urbanity",
   "type": "esriFieldTypeString",
   "alias": "urbanity",
   "length": 1
  },
  {
   "name": "superlot",
   "type": "esriFieldTypeString",
   "alias": "superlot",
   "length": 1
  },
  {
   "name": "housenumber",
   "type": "esriFieldTypeString",
   "alias": "housenumber",
   "length": 20
  },
  {
   "name": "address",
   "type": "esriFieldTypeString",
   "alias": "address",
   "length": 100
  },
  {
   "name": "_x_centroid",
   "type": "esriFieldTypeDouble",
   "alias": "_x_centroid"
  },
  {
   "name": "_y_centroid",
   "type": "esriFieldTypeDouble",
   "alias": "_y_centroid"
  },
  {
   "name": "shape_Length",
   "type": "esriFieldTypeDouble",
   "alias": "shape_Length"
  },
  {
   "name": "shape_Area",
   "type": "esriFieldTypeDouble",
   "alias": "shape_Area"
  }
 ],
 "features": [
  {
   "attributes": {
    "OBJECTID": 2503756,
    "createdate": 1412107933000,
    "gurasid": 50597729,
    "principaladdresssiteoid": 1115275,
    "propertytype": 1,
    "valnetpropertystatus": 2,
    "valnetpropertytype": 2,
    "dissolveparcelcount": 1,
    "valnetlotcount": 1,
    "valnetworkflowid": null,
    "propid": 2426646,
    "uuid": "b3eaf0f1-4eb1-3304-8eb9-d37c6075ee7c",
    "urbanity": "U",
    "superlot": "N",
    "housenumber": "108-122",
    "address": "108-122 TOWNVIEW ROAD MOUNT PRITCHARD",
    "_x_centroid": null,
    "_y_centroid": null,
    "shape_Length": 868.61524083241557,
    "shape_Area": 38053.209528979234
   },
   "geometry": {
    "rings": [
     [
      [
       16799518.442874998,
       -4016213.2877499983
      ],
      [
       16799440.695124999,
       -4016215.8066250011
      ],
      [
       16799422.101875,
       -4016190.5158750005
      ],
      [
       16799421.869374998,
       -4016190.2933750004
      ],
      [
       16799408.7575,
       -4016172.1228750013
      ],
      [
       16799399.97225,
       -4016169.818
      ],
      [
       16799340.577249996,
       -4016090.9224999994
      ],
      [
       16799342.390375003,
       -4016082.2166250013
      ],
      [
       16799346.437749997,
       -4016080.4828750007
      ],
      [
       16799350.446249999,
       -4016078.6602500007
      ],
      [
       16799354.41375,
       -4016076.7473750003
      ],
      [
       16799358.338375002,
       -4016074.7467500009
      ],
      [
       16799362.217,
       -4016072.6607500017
      ],
      [
       16799366.048874997,
       -4016070.4869999997
      ],
      [
       16799369.83275,
       -4016068.2289999984
      ],
      [
       16799373.564750001,
       -4016065.8881249987
      ],
      [
       16799377.243874997,
       -4016063.4631250016
      ],
      [
       16799380.869125001,
       -4016060.9574999996
      ],
      [
       16799384.438500002,
       -4016058.3726250008
      ],
      [
       16799387.950000003,
       -4016055.7082500011
      ],
      [
       16799391.402625002,
       -4016052.9658749998
      ],
      [
       16799394.791374996,
       -4016050.1476249993
      ],
      [
       16799395.380125001,
       -4016049.6354999989
      ],
      [
       16799398.118249997,
       -4016047.2537500001
      ],
      [
       16799401.381250001,
       -4016044.2863750011
      ],
      [
       16799404.577375002,
       -4016041.2493750006
      ],
      [
       16799407.704750001,
       -4016038.1402500011
      ],
      [
       16799410.764124997,
       -4016034.9613750018
      ],
      [
       16799413.75175,
       -4016031.7163750008
      ],
      [
       16799415.19675,
       -4016030.0764999986
      ],
      [
       16799416.715499997,
       -4016028.3414999992
      ],
      [
       16799419.649125002,
       -4016024.8379999995
      ],
      [
       16799422.505125001,
       -4016021.2719999999
      ],
      [
       16799425.280125,
       -4016017.641125001
      ],
      [
       16799427.977375001,
       -4016013.9488749988
      ],
      [
       16799430.590750001,
       -4016010.1988749988
      ],
      [
       16799431.646499999,
       -4016008.6094999984
      ],
      [
       16799433.120375,
       -4016006.3900000006
      ],
      [
       16799435.566124998,
       -4016002.5269999988
      ],
      [
       16799436.205750003,
       -4016001.4653749987
      ],
      [
       16799437.903125003,
       -4015998.6099999994
      ],
      [
       16799439.334124997,
       -4015996.0755000003
      ],
      [
       16799440.116374999,
       -4015994.707249999
      ],
      [
       16799442.191,
       -4015990.8792500012
      ],
      [
       16799444.18175,
       -4015987.0066250004
      ],
      [
       16799446.087624997,
       -4015983.0920000002
      ],
      [
       16799447.903750002,
       -4015979.1339999996
      ],
      [
       16799449.634000003,
       -4015975.1376250014
      ],
      [
       16799451.2755,
       -4015971.103875
      ],
      [
       16799452.827249996,
       -4015967.0328750014
      ],
      [
       16799454.289125003,
       -4015962.9294999987
      ],
      [
       16799455.659125,
       -4015958.7948749997
      ],
      [
       16799456.938375004,
       -4015954.6288749985
      ],
      [
       16799458.124875002,
       -4015950.4365000017
      ],
      [
       16799459.219499998,
       -4015946.2201250009
      ],
      [
       16799460.219374999,
       -4015941.978374999
      ],
      [
       16799461.125500001,
       -4015937.7162499987
      ],
      [
       16799461.938749999,
       -4015933.4361249991
      ],
      [
       16799462.65625,
       -4015929.1380000003
      ],
      [
       16799463.278875001,
       -4015924.8241249993
      ],
      [
       16799463.805749997,
       -4015920.4983749986
      ],
      [
       16799464.237750001,
       -4015916.16175
      ],
      [
       16799464.573124997,
       -4015911.8178750016
      ],
      [
       16799464.813625,
       -4015907.4643750004
      ],
      [
       16799464.957249999,
       -4015903.1085000001
      ],
      [
       16799469.776000001,
       -4015898.5170000009
      ],
      [
       16799471.8345,
       -4015897.7800000012
      ],
      [
       16799473.924125001,
       -4015897.1307500005
      ],
      [
       16799476.038625002,
       -4015896.5764999986
      ],
      [
       16799478.174999997,
       -4015896.1136250012
      ],
      [
       16799480.330375001,
       -4015895.7445
      ],
      [
       16799482.498750001,
       -4015895.4691249989
      ],
      [
       16799484.677124999,
       -4015895.2899999991
      ],
      [
       16799486.861374997,
       -4015895.2046249993
      ],
      [
       16799489.046750002,
       -4015895.2155000009
      ],
      [
       16799491.231124997,
       -4015895.3201249987
      ],
      [
       16799493.407375,
       -4015895.5196250007
      ],
      [
       16799495.573749997,
       -4015895.8153750002
      ],
      [
       16799497.725125,
       -4015896.2037499994
      ],
      [
       16799499.856624998,
       -4015896.6871250011
      ],
      [
       16799501.967124999,
       -4015897.2617500015
      ],
      [
       16799504.049625002,
       -4015897.927875001
      ],
      [
       16799506.10125,
       -4015898.6841249987
      ],
      [
       16799549.829750001,
       -4015915.0965000018
      ],
      [
       16799541.535499997,
       -4015967.7783749998
      ],
      [
       16799537.619874999,
       -4016009.4041250013
      ],
      [
       16799518.442874998,
       -4016213.2877499983
      ]
     ]
    ]
   }
  }
 ]
}